topsis/102017148.py
topsis/__init__.py
topsis_raunak_102017148-1.0.0.dist-info/LICENSE
topsis_raunak_102017148-1.0.0.dist-info/METADATA
topsis_raunak_102017148-1.0.0.dist-info/WHEEL
topsis_raunak_102017148-1.0.0.dist-info/entry_points.txt
topsis_raunak_102017148-1.0.0.dist-info/top_level.txt
topsis_raunak_102017148-1.0.0.dist-info/RECORD
