Metadata-Version: 2.1
Name: topsis-raunak-102017148
Version: 1.0.0
Summary: A Python package to get optimal solutiion.
Author: Raunak Kumar
Author-email: raunakkumar071201@gmail.com
License: MIT
Classifier: License :: OSI Approved :: MIT License
Classifier: Programming Language :: Python :: 3
Classifier: Programming Language :: Python :: 3.7
License-File: LICENSE
Requires-Dist: pandas
Requires-Dist: numpy
